Workbook

Sheet PolicyActions
A1: id | B1: action | C1: type
A2: 1 | B2: Expansionary fiscal policy | C2: fiscal_policy
A3: 2 | B3: Increase government spending | C3: fiscal_policy
A4: 3 | B4: Increase transfer payments (e.g. unemployment benefits) | C4: fiscal_policy
A5: 4 | B5: Decrease taxes | C5: fiscal_policy
A6: 5 | B6: Contractionary fiscal policy | C6: fiscal_policy
A7: 6 | B7: Decrease government spending | C7: fiscal_policy
A8: 7 | B8: Decrease transfer payments | C8: fiscal_policy
A9: 8 | B9: Increase taxes | C9: fiscal_policy
A10: 9 | B10: Expansionary monetary policy | C10: monetary_policy
A11: 10 | B11: Decrease required reserve ratio | C11: monetary_policy
A12: 11 | B12: Decrease reserve requirement | C12: monetary_policy
A13: 12 | B13: Buy government bonds / securities | C13: monetary_policy
... A27: 26 | B27: Increase administered interest rates | C27: monetary_policy

Sheet EconomicVariables
A1: id | B1: name | C1: category
A2: 1 | B2: Aggregate Demand | C2: macro_indicator
A3: 2 | B3: Price Level | C3: macro_indicator
A4: 3 | B4: Real GDP | C4: macro_indicator
A5: 4 | B5: Unemployment Rate | C5: macro_indicator
A6: 5 | B6: Money Supply | C6: financial_indicator
A7: 6 | B7: Interest Rate | C7: financial_indicator
A8: 7 | B8: Bond Price | C8: financial_indicator
A9: 8 | B9: Interest-sensitive Private Spending (Investment & Consumption) | C9: expenditure
A10: 9 | B10: Economic Growth (LRAS, PPC) | C10: macro_indicator

Sheet PolicyEffects
A1: policyId | C1: variableId | E1: effect | F1: explanation
A2: 1 | B2: =VLOOKUP(A2,PolicyActions!A:B,2,FALSE) -> Expansionary fiscal policy | C2: 1 | D2: =VLOOKUP(C2,EconomicVariables!A:B,2,FALSE) -> Aggregate Demand | E2: increase | F2: Expansionary fiscal policy刺激经济，增加AD。政府支出直接影响AD，税和转移支付影响disposable income，间接影响private spending和AD。（但如有deficit，政府借债可能会crowd out部分private spending）
A3: 1 | B3: =VLOOKUP(A3,PolicyActions!A:B,2,FALSE) -> Expansionary fiscal policy | C3: 2 | D3: =VLOOKUP(C3,EconomicVariables!A:B,2,FALSE) -> Price Level | E3: increase | F3: Expansionary fiscal policy刺激经济，增加AD，见AD-AS diagram
A4: 1 | B4: =VLOOKUP(A4,PolicyActions!A:B,2,FALSE) -> Expansionary fiscal policy | C4: 3 | D4: =VLOOKUP(C4,EconomicVariables!A:B,2,FALSE) -> Real GDP | E4: increase | F4: Expansionary fiscal policy刺激经济，增加AD，见AD-AS diagram
A5: 1 | B5: =VLOOKUP(A5,PolicyActions!A:B,2,FALSE) -> Expansionary fiscal policy | C5: 4 | D5: =VLOOKUP(C5,EconomicVariables!A:B,2,FALSE) -> Unemployment Rate | E5: decrease | F5: 失业率通常与real GDP反向。（Expansionary fiscal policy刺激经济，增加AD，见AD-AS diagram）
A6: 1 | B6: =VLOOKUP(A6,PolicyActions!A:B,2,FALSE) -> Expansionary fiscal policy | C6: 6 | D6: =VLOOKUP(C6,EconomicVariables!A:B,2,FALSE) -> Interest Rate | E6: increase | F6: Expansionary fiscal policy使public savings=tax-(government spending+transfers)降低，减少Supply of Loans（或增加deficit spending进而增加Demand for Loans)，因而利率上升。见loanable funds market diagram
A7: 1 | B7: =VLOOKUP(A7,PolicyActions!A:B,2,FALSE) -> Expansionary fiscal policy | C7: 7 | D7: =VLOOKUP(C7,EconomicVariables!A:B,2,FALSE) -> Bond Price | E7: decrease | F7: 债券价格与利率反向。（Expansionary fiscal policy使public savings=tax-(government spending+transfers)降低，减少Supply of Loans（或增加deficit spending进而增加Demand for Loans)，因而利率上升。见loanable funds market diagram）
A8: 1 | B8: =VLOOKUP(A8,PolicyActions!A:B,2,FALSE) -> Expansionary fiscal policy | C8: 8 | D8: =VLOOKUP(C8,EconomicVariables!A:B,2,FALSE) -> Interest-sensitive Private Spending (Investment & Consumption) | E8: decrease | F8: Interest-sensitive Private Spending (Investment & Consumption)与利率反向。（Expansionary fiscal policy使public savings=tax-(government spending+transfers)降低，减少Supply of Loans（或增加deficit spending进而增加Demand for Loans)，因而利率上升。见loanable funds market diagram）
A9: 1 | B9: =VLOOKUP(A9,PolicyActions!A:B,2,FALSE) -> Expansionary fiscal policy | C9: 9 | D9: =VLOOKUP(C9,EconomicVariables!A:B,2,FALSE) -> Economic Growth (LRAS, PPC) | E9: decrease | F9: Investment与利率反向，长期会影响capital stock资本存量（属于资源数量）和潜在产能。（Expansionary fiscal policy使public savings=tax-(government spending+transfers)降低，减少Supply of Loans（或增加deficit spending进而增加Demand for Loans)，因而利率上升。见loanable funds market diagram）
A10: 2 | B10: =VLOOKUP(A10,PolicyActions!A:B,2,FALSE) -> Increase government spending | C10: 1 | D10: =VLOOKUP(C10,EconomicVariables!A:B,2,FALSE) -> Aggregate Demand | E10: increase | F10: =F2 -> Expansionary fiscal policy刺激经济，增加AD。政府支出直接影响AD，税和转移支付影响disposable income，间接影响private spending和AD。（但如有deficit，政府借债可能会crowd out部分private spending）
A11: 2 | B11: =VLOOKUP(A11,PolicyActions!A:B,2,FALSE) -> Increase government spending | C11: 2 | D11: =VLOOKUP(C11,EconomicVariables!A:B,2,FALSE) -> Price Level | E11: increase | F11: =F3 -> Expansionary fiscal policy刺激经济，增加AD，见AD-AS diagram
A12: 2 | B12: =VLOOKUP(A12,PolicyActions!A:B,2,FALSE) -> Increase government spending | C12: 3 | D12: =VLOOKUP(C12,EconomicVariables!A:B,2,FALSE) -> Real GDP | E12: increase | F12: =F4 -> Expansionary fiscal policy刺激经济，增加AD，见AD-AS diagram
A13: 2 | B13: =VLOOKUP(A13,PolicyActions!A:B,2,FALSE) -> Increase government spending | C13: 4 | D13: =VLOOKUP(C13,EconomicVariables!A:B,2,FALSE) -> Unemployment Rate | E13: decrease | F13: =F5 -> 失业率通常与real GDP反向。（Expansionary fiscal policy刺激经济，增加AD，见AD-AS diagram）
A14: 2 | B14: =VLOOKUP(A14,PolicyActions!A:B,2,FALSE) -> Increase government spending | C14: 6 | D14: =VLOOKUP(C14,EconomicVariables!A:B,2,FALSE) -> Interest Rate | E14: increase | F14: =F6 -> Expansionary fiscal policy使public savings=tax-(government spending+transfers)降低，减少Supply of Loans（或增加deficit spending进而增加Demand for Loans)，因而利率上升。见loanable funds market diagram
A15: 2 | B15: =VLOOKUP(A15,PolicyActions!A:B,2,FALSE) -> Increase government spending | C15: 7 | D15: =VLOOKUP(C15,EconomicVariables!A:B,2,FALSE) -> Bond Price | E15: decrease | F15: =F7 -> 债券价格与利率反向。（Expansionary fiscal policy使public savings=tax-(government spending+transfers)降低，减少Supply of Loans（或增加deficit spending进而增加Demand for Loans)，因而利率上升。见loanable funds market diagram）
A16: 2 | B16: =VLOOKUP(A16,PolicyActions!A:B,2,FALSE) -> Increase government spending | C16: 8 | D16: =VLOOKUP(C16,EconomicVariables!A:B,2,FALSE) -> Interest-sensitive Private Spending (Investment & Consumption) | E16: decrease | F16: =F8 -> Interest-sensitive Private Spending (Investment & Consumption)与利率反向。（Expansionary fiscal policy使public savings=tax-(government spending+transfers)降低，减少Supply of Loans（或增加deficit spending进而增加Demand for Loans)，因而利率上升。见loanable funds market diagram）
A17: 2 | B17: =VLOOKUP(A17,PolicyActions!A:B,2,FALSE) -> Increase government spending | C17: 9 | D17: =VLOOKUP(C17,EconomicVariables!A:B,2,FALSE) -> Economic Growth (LRAS, PPC) | E17: decrease | F17: =F9 -> Investment与利率反向，长期会影响capital stock资本存量（属于资源数量）和潜在产能。（Expansionary fiscal policy使public savings=tax-(government spending+transfers)降低，减少Supply of Loans（或增加deficit spending进而增加Demand for Loans)，因而利率上升。见loanable funds market diagram）
A18: 3 | B18: =VLOOKUP(A18,PolicyActions!A:B,2,FALSE) -> Increase transfer payments (e.g. unemployment benefits) | C18: 1 | D18: =VLOOKUP(C18,EconomicVariables!A:B,2,FALSE) -> Aggregate Demand | E18: increase | F18: =F10 -> Expansionary fiscal policy刺激经济，增加AD。政府支出直接影响AD，税和转移支付影响disposable income，间接影响private spending和AD。（但如有deficit，政府借债可能会crowd out部分private spending）
A19: 3 | B19: =VLOOKUP(A19,PolicyActions!A:B,2,FALSE) -> Increase transfer payments (e.g. unemployment benefits) | C19: 2 | D19: =VLOOKUP(C19,EconomicVariables!A:B,2,FALSE) -> Price Level | E19: increase | F19: =F11 -> Expansionary fiscal policy刺激经济，增加AD，见AD-AS diagram
A20: 3 | B20: =VLOOKUP(A20,PolicyActions!A:B,2,FALSE) -> Increase transfer payments (e.g. unemployment benefits) | C20: 3 | D20: =VLOOKUP(C20,EconomicVariables!A:B,2,FALSE) -> Real GDP | E20: increase | F20: =F12 -> Expansionary fiscal policy刺激经济，增加AD，见AD-AS diagram
A21: 3 | B21: =VLOOKUP(A21,PolicyActions!A:B,2,FALSE) -> Increase transfer payments (e.g. unemployment benefits) | C21: 4 | D21: =VLOOKUP(C21,EconomicVariables!A:B,2,FALSE) -> Unemployment Rate | E21: decrease | F21: =F13 -> 失业率通常与real GDP反向。（Expansionary fiscal policy刺激经济，增加AD，见AD-AS diagram）
... A33: 4 | B33: =VLOOKUP(A33,PolicyActions!A:B,2,FALSE) -> Decrease taxes | C33: 9 | D33: =VLOOKUP(C33,EconomicVariables!A:B,2,FALSE) -> Economic Growth (LRAS, PPC) | E33: decrease | F33: =F25 -> Investment与利率反向，长期会影响capital stock资本存量（属于资源数量）和潜在产能。（Expansionary fiscal policy使public savings=tax-(government spending+transfers)降低，减少Supply of Loans（或增加deficit spending进而增加Demand for Loans)，因而利率上升。见loanable funds market diagram）
A34: 5 | B34: =VLOOKUP(A34,PolicyActions!A:B,2,FALSE) -> Contractionary fiscal policy | C34: 1 | D34: =VLOOKUP(C34,EconomicVariables!A:B,2,FALSE) -> Aggregate Demand | E34: decrease | F34: Contractionary fiscal policy减少AD，政府支出直接影响AD，税和转移支付影响disposable income，间接影响private spending和AD。
A35: 5 | B35: =VLOOKUP(A35,PolicyActions!A:B,2,FALSE) -> Contractionary fiscal policy | C35: 2 | D35: =VLOOKUP(C35,EconomicVariables!A:B,2,FALSE) -> Price Level | E35: decrease | F35: Contractionary fiscal policy减少AD，见AD-AS diagram
A36: 5 | B36: =VLOOKUP(A36,PolicyActions!A:B,2,FALSE) -> Contractionary fiscal policy | C36: 3 | D36: =VLOOKUP(C36,EconomicVariables!A:B,2,FALSE) -> Real GDP | E36: decrease | F36: Contractionary fiscal policy减少AD，见AD-AS diagram
A37: 5 | B37: =VLOOKUP(A37,PolicyActions!A:B,2,FALSE) -> Contractionary fiscal policy | C37: 4 | D37: =VLOOKUP(C37,EconomicVariables!A:B,2,FALSE) -> Unemployment Rate | E37: increase | F37: 失业率通常与real GDP反向。（Contractionary fiscal policy减少AD，见AD-AS diagram）
A38: 5 | B38: =VLOOKUP(A38,PolicyActions!A:B,2,FALSE) -> Contractionary fiscal policy | C38: 6 | D38: =VLOOKUP(C38,EconomicVariables!A:B,2,FALSE) -> Interest Rate | E38: decrease | F38: Contractionary fiscal policy使public savings=tax-(government spending+transfers)增加，增加Supply of Loans（或减少deficit spending进而减少Demand for Loans)，因而利率下降。见loanable funds market diagram
A39: 5 | B39: =VLOOKUP(A39,PolicyActions!A:B,2,FALSE) -> Contractionary fiscal policy | C39: 7 | D39: =VLOOKUP(C39,EconomicVariables!A:B,2,FALSE) -> Bond Price | E39: increase | F39: 债券价格与利率反向。（Contractionary fiscal policy使public savings=tax-(government spending+transfers)增加，增加Supply of Loans（或减少deficit spending进而减少Demand for Loans)，因而利率下降。见loanable funds market diagram）
A40: 5 | B40: =VLOOKUP(A40,PolicyActions!A:B,2,FALSE) -> Contractionary fiscal policy | C40: 8 | D40: =VLOOKUP(C40,EconomicVariables!A:B,2,FALSE) -> Interest-sensitive Private Spending (Investment & Consumption) | E40: increase | F40: Interest-sensitive Private Spending (Investment & Consumption)与利率反向。（Contractionary fiscal policy使public savings=tax-(government spending+transfers)增加，增加Supply of Loans（或减少deficit spending进而减少Demand for Loans)，因而利率下降。见loanable funds market diagram）
A41: 5 | B41: =VLOOKUP(A41,PolicyActions!A:B,2,FALSE) -> Contractionary fiscal policy | C41: 9 | D41: =VLOOKUP(C41,EconomicVariables!A:B,2,FALSE) -> Economic Growth (LRAS, PPC) | E41: increase | F41: Investment与利率反向，长期会影响capital stock资本存量（属于资源数量）和潜在产能。（Contractionary fiscal policy使public savings=tax-(government spending+transfers)增加，增加Supply of Loans（或减少deficit spending进而减少Demand for Loans)，因而利率下降。见loanable funds market diagram）
A42: 6 | B42: =VLOOKUP(A42,PolicyActions!A:B,2,FALSE) -> Decrease government spending | C42: 1 | D42: =VLOOKUP(C42,EconomicVariables!A:B,2,FALSE) -> Aggregate Demand | E42: decrease | F42: =F34 -> Contractionary fiscal policy减少AD，政府支出直接影响AD，税和转移支付影响disposable income，间接影响private spending和AD。
A43: 6 | B43: =VLOOKUP(A43,PolicyActions!A:B,2,FALSE) -> Decrease government spending | C43: 2 | D43: =VLOOKUP(C43,EconomicVariables!A:B,2,FALSE) -> Price Level | E43: decrease | F43: =F35 -> Contractionary fiscal policy减少AD，见AD-AS diagram
A44: 6 | B44: =VLOOKUP(A44,PolicyActions!A:B,2,FALSE) -> Decrease government spending | C44: 3 | D44: =VLOOKUP(C44,EconomicVariables!A:B,2,FALSE) -> Real GDP | E44: decrease | F44: =F36 -> Contractionary fiscal policy减少AD，见AD-AS diagram
A45: 6 | B45: =VLOOKUP(A45,PolicyActions!A:B,2,FALSE) -> Decrease government spending | C45: 4 | D45: =VLOOKUP(C45,EconomicVariables!A:B,2,FALSE) -> Unemployment Rate | E45: increase | F45: =F37 -> 失业率通常与real GDP反向。（Contractionary fiscal policy减少AD，见AD-AS diagram）
A46: 6 | B46: =VLOOKUP(A46,PolicyActions!A:B,2,FALSE) -> Decrease government spending | C46: 6 | D46: =VLOOKUP(C46,EconomicVariables!A:B,2,FALSE) -> Interest Rate | E46: decrease | F46: =F38 -> Contractionary fiscal policy使public savings=tax-(government spending+transfers)增加，增加Supply of Loans（或减少deficit spending进而减少Demand for Loans)，因而利率下降。见loanable funds market diagram
A47: 6 | B47: =VLOOKUP(A47,PolicyActions!A:B,2,FALSE) -> Decrease government spending | C47: 7 | D47: =VLOOKUP(C47,EconomicVariables!A:B,2,FALSE) -> Bond Price | E47: increase | F47: =F39 -> 债券价格与利率反向。（Contractionary fiscal policy使public savings=tax-(government spending+transfers)增加，增加Supply of Loans（或减少deficit spending进而减少Demand for Loans)，因而利率下降。见loanable funds market diagram）
A48: 6 | B48: =VLOOKUP(A48,PolicyActions!A:B,2,FALSE) -> Decrease government spending | C48: 8 | D48: =VLOOKUP(C48,EconomicVariables!A:B,2,FALSE) -> Interest-sensitive Private Spending (Investment & Consumption) | E48: increase | F48: =F40 -> Interest-sensitive Private Spending (Investment & Consumption)与利率反向。（Contractionary fiscal policy使public savings=tax-(government spending+transfers)增加，增加Supply of Loans（或减少deficit spending进而减少Demand for Loans)，因而利率下降。见loanable funds market diagram）
A49: 6 | B49: =VLOOKUP(A49,PolicyActions!A:B,2,FALSE) -> Decrease government spending | C49: 9 | D49: =VLOOKUP(C49,EconomicVariables!A:B,2,FALSE) -> Economic Growth (LRAS, PPC) | E49: increase | F49: =F41 -> Investment与利率反向，长期会影响capital stock资本存量（属于资源数量）和潜在产能。（Contractionary fiscal policy使public savings=tax-(government spending+transfers)增加，增加Supply of Loans（或减少deficit spending进而减少Demand for Loans)，因而利率下降。见loanable funds market diagram）
A50: 7 | B50: =VLOOKUP(A50,PolicyActions!A:B,2,FALSE) -> Decrease transfer payments | C50: 1 | D50: =VLOOKUP(C50,EconomicVariables!A:B,2,FALSE) -> Aggregate Demand | E50: decrease | F50: =F42 -> Contractionary fiscal policy减少AD，政府支出直接影响AD，税和转移支付影响disposable income，间接影响private spending和AD。
A51: 7 | B51: =VLOOKUP(A51,PolicyActions!A:B,2,FALSE) -> Decrease transfer payments | C51: 2 | D51: =VLOOKUP(C51,EconomicVariables!A:B,2,FALSE) -> Price Level | E51: decrease | F51: =F43 -> Contractionary fiscal policy减少AD，见AD-AS diagram
A52: 7 | B52: =VLOOKUP(A52,PolicyActions!A:B,2,FALSE) -> Decrease transfer payments | C52: 3 | D52: =VLOOKUP(C52,EconomicVariables!A:B,2,FALSE) -> Real GDP | E52: decrease | F52: =F44 -> Contractionary fiscal policy减少AD，见AD-AS diagram
A53: 7 | B53: =VLOOKUP(A53,PolicyActions!A:B,2,FALSE) -> Decrease transfer payments | C53: 4 | D53: =VLOOKUP(C53,EconomicVariables!A:B,2,FALSE) -> Unemployment Rate | E53: increase | F53: =F45 -> 失业率通常与real GDP反向。（Contractionary fiscal policy减少AD，见AD-AS diagram）
... A65: 8 | B65: =VLOOKUP(A65,PolicyActions!A:B,2,FALSE) -> Increase taxes | C65: 9 | D65: =VLOOKUP(C65,EconomicVariables!A:B,2,FALSE) -> Economic Growth (LRAS, PPC) | E65: increase | F65: =F57 -> Investment与利率反向，长期会影响capital stock资本存量（属于资源数量）和潜在产能。（Contractionary fiscal policy使public savings=tax-(government spending+transfers)增加，增加Supply of Loans（或减少deficit spending进而减少Demand for Loans)，因而利率下降。见loanable funds market diagram）
A66: 9 | B66: =VLOOKUP(A66,PolicyActions!A:B,2,FALSE) -> Expansionary monetary policy | C66: 1 | D66: =VLOOKUP(C66,EconomicVariables!A:B,2,FALSE) -> Aggregate Demand | E66: increase | F66: Expansionary monetary policy刺激经济，通过降利率，增加interest-sensitive private spending和AD
A67: 9 | B67: =VLOOKUP(A67,PolicyActions!A:B,2,FALSE) -> Expansionary monetary policy | C67: 2 | D67: =VLOOKUP(C67,EconomicVariables!A:B,2,FALSE) -> Price Level | E67: increase | F67: Expansionary monetary policy刺激经济，降利率，增加AD，见AD-AS diagram
A68: 9 | B68: =VLOOKUP(A68,PolicyActions!A:B,2,FALSE) -> Expansionary monetary policy | C68: 3 | D68: =VLOOKUP(C68,EconomicVariables!A:B,2,FALSE) -> Real GDP | E68: increase | F68: Expansionary monetary policy刺激经济，降利率，增加AD，见AD-AS diagram
A69: 9 | B69: =VLOOKUP(A69,PolicyActions!A:B,2,FALSE) -> Expansionary monetary policy | C69: 4 | D69: =VLOOKUP(C69,EconomicVariables!A:B,2,FALSE) -> Unemployment Rate | E69: decrease | F69: 失业率通常与real GDP反向。（Expansionary monetary policy刺激经济，降利率，增加AD，见AD-AS diagram）
A70: 9 | B70: =VLOOKUP(A70,PolicyActions!A:B,2,FALSE) -> Expansionary monetary policy | C70: 5 | D70: =VLOOKUP(C70,EconomicVariables!A:B,2,FALSE) -> Money Supply | E70: increase | F70: Expansionary monetary policy中buy bonds可增加monetary base，降reserve requirement可提高money multiplier和money supply
A71: 9 | B71: =VLOOKUP(A71,PolicyActions!A:B,2,FALSE) -> Expansionary monetary policy | C71: 6 | D71: =VLOOKUP(C71,EconomicVariables!A:B,2,FALSE) -> Interest Rate | E71: decrease | F71: Expansionary monetary policy增加money supply，降利率（见money market diagram & reserve market diagram)
A72: 9 | B72: =VLOOKUP(A72,PolicyActions!A:B,2,FALSE) -> Expansionary monetary policy | C72: 7 | D72: =VLOOKUP(C72,EconomicVariables!A:B,2,FALSE) -> Bond Price | E72: increase | F72: 债券价格与利率反向。（Expansionary monetary policy刺激经济，降利率，增加AD）
A73: 9 | B73: =VLOOKUP(A73,PolicyActions!A:B,2,FALSE) -> Expansionary monetary policy | C73: 8 | D73: =VLOOKUP(C73,EconomicVariables!A:B,2,FALSE) -> Interest-sensitive Private Spending (Investment & Consumption) | E73: increase | F73: Interest-sensitive Private Spending (Investment & Consumption)与利率反向。（Expansionary monetary policy刺激经济，降利率，增加AD）
A74: 9 | B74: =VLOOKUP(A74,PolicyActions!A:B,2,FALSE) -> Expansionary monetary policy | C74: 9 | D74: =VLOOKUP(C74,EconomicVariables!A:B,2,FALSE) -> Economic Growth (LRAS, PPC) | E74: increase | F74: Investment与利率反向，长期会影响capital stock资本存量（属于资源数量）和潜在产能。（Expansionary monetary policy刺激经济，降利率，增加AD）
A75: 10 | B75: =VLOOKUP(A75,PolicyActions!A:B,2,FALSE) -> Decrease required reserve ratio | C75: 1 | D75: =VLOOKUP(C75,EconomicVariables!A:B,2,FALSE) -> Aggregate Demand | E75: increase | F75: =F66 -> Expansionary monetary policy刺激经济，通过降利率，增加interest-sensitive private spending和AD
A76: 10 | B76: =VLOOKUP(A76,PolicyActions!A:B,2,FALSE) -> Decrease required reserve ratio | C76: 2 | D76: =VLOOKUP(C76,EconomicVariables!A:B,2,FALSE) -> Price Level | E76: increase | F76: =F67 -> Expansionary monetary policy刺激经济，降利率，增加AD，见AD-AS diagram
A77: 10 | B77: =VLOOKUP(A77,PolicyActions!A:B,2,FALSE) -> Decrease required reserve ratio | C77: 3 | D77: =VLOOKUP(C77,EconomicVariables!A:B,2,FALSE) -> Real GDP | E77: increase | F77: =F68 -> Expansionary monetary policy刺激经济，降利率，增加AD，见AD-AS diagram
A78: 10 | B78: =VLOOKUP(A78,PolicyActions!A:B,2,FALSE) -> Decrease required reserve ratio | C78: 4 | D78: =VLOOKUP(C78,EconomicVariables!A:B,2,FALSE) -> Unemployment Rate | E78: decrease | F78: =F69 -> 失业率通常与real GDP反向。（Expansionary monetary policy刺激经济，降利率，增加AD，见AD-AS diagram）
A79: 10 | B79: =VLOOKUP(A79,PolicyActions!A:B,2,FALSE) -> Decrease required reserve ratio | C79: 5 | D79: =VLOOKUP(C79,EconomicVariables!A:B,2,FALSE) -> Money Supply | E79: increase | F79: =F70 -> Expansionary monetary policy中buy bonds可增加monetary base，降reserve requirement可提高money multiplier和money supply
A80: 10 | B80: =VLOOKUP(A80,PolicyActions!A:B,2,FALSE) -> Decrease required reserve ratio | C80: 6 | D80: =VLOOKUP(C80,EconomicVariables!A:B,2,FALSE) -> Interest Rate | E80: decrease | F80: =F71 -> Expansionary monetary policy增加money supply，降利率（见money market diagram & reserve market diagram)
A81: 10 | B81: =VLOOKUP(A81,PolicyActions!A:B,2,FALSE) -> Decrease required reserve ratio | C81: 7 | D81: =VLOOKUP(C81,EconomicVariables!A:B,2,FALSE) -> Bond Price | E81: increase | F81: =F72 -> 债券价格与利率反向。（Expansionary monetary policy刺激经济，降利率，增加AD）
A82: 10 | B82: =VLOOKUP(A82,PolicyActions!A:B,2,FALSE) -> Decrease required reserve ratio | C82: 8 | D82: =VLOOKUP(C82,EconomicVariables!A:B,2,FALSE) -> Interest-sensitive Private Spending (Investment & Consumption) | E82: increase | F82: =F73 -> Interest-sensitive Private Spending (Investment & Consumption)与利率反向。（Expansionary monetary policy刺激经济，降利率，增加AD）
A83: 10 | B83: =VLOOKUP(A83,PolicyActions!A:B,2,FALSE) -> Decrease required reserve ratio | C83: 9 | D83: =VLOOKUP(C83,EconomicVariables!A:B,2,FALSE) -> Economic Growth (LRAS, PPC) | E83: increase | F83: =F74 -> Investment与利率反向，长期会影响capital stock资本存量（属于资源数量）和潜在产能。（Expansionary monetary policy刺激经济，降利率，增加AD）
A84: 11 | B84: =VLOOKUP(A84,PolicyActions!A:B,2,FALSE) -> Decrease reserve requirement | C84: 1 | D84: =VLOOKUP(C84,EconomicVariables!A:B,2,FALSE) -> Aggregate Demand | E84: increase | F84: =F75 -> Expansionary monetary policy刺激经济，通过降利率，增加interest-sensitive private spending和AD
A85: 11 | B85: =VLOOKUP(A85,PolicyActions!A:B,2,FALSE) -> Decrease reserve requirement | C85: 2 | D85: =VLOOKUP(C85,EconomicVariables!A:B,2,FALSE) -> Price Level | E85: increase | F85: =F76 -> Expansionary monetary policy刺激经济，降利率，增加AD，见AD-AS diagram
A86: 11 | B86: =VLOOKUP(A86,PolicyActions!A:B,2,FALSE) -> Decrease reserve requirement | C86: 3 | D86: =VLOOKUP(C86,EconomicVariables!A:B,2,FALSE) -> Real GDP | E86: increase | F86: =F77 -> Expansionary monetary policy刺激经济，降利率，增加AD，见AD-AS diagram
... A123: 15 | B123: =VLOOKUP(A123,PolicyActions!A:B,2,FALSE) -> Decrease discount rate | C123: 4 | D123: =VLOOKUP(C123,EconomicVariables!A:B,2,FALSE) -> Unemployment Rate | E123: decrease | F123: =F114 -> 失业率通常与real GDP反向。（Expansionary monetary policy刺激经济，降利率，增加AD，见AD-AS diagram）
A124: 15 | B124: =VLOOKUP(A124,PolicyActions!A:B,2,FALSE) -> Decrease discount rate | C124: 6 | D124: =VLOOKUP(C124,EconomicVariables!A:B,2,FALSE) -> Interest Rate | E124: decrease | F124: Expansionary monetary policy降利率。Discount rate（federal funds rate上限）和IOR（federal funds rate下限）属于administered interest rate，央行可直接设定，用于调控市场利率的基准federal funds rate（见reserve market diagram)。 这三者都属于policy rate。
A125: 15 | B125: =VLOOKUP(A125,PolicyActions!A:B,2,FALSE) -> Decrease discount rate | C125: 7 | D125: =VLOOKUP(C125,EconomicVariables!A:B,2,FALSE) -> Bond Price | E125: increase | F125: =F117 -> 债券价格与利率反向。（Expansionary monetary policy刺激经济，降利率，增加AD）
A126: 15 | B126: =VLOOKUP(A126,PolicyActions!A:B,2,FALSE) -> Decrease discount rate | C126: 8 | D126: =VLOOKUP(C126,EconomicVariables!A:B,2,FALSE) -> Interest-sensitive Private Spending (Investment & Consumption) | E126: increase | F126: =F118 -> Interest-sensitive Private Spending (Investment & Consumption)与利率反向。（Expansionary monetary policy刺激经济，降利率，增加AD）
A127: 15 | B127: =VLOOKUP(A127,PolicyActions!A:B,2,FALSE) -> Decrease discount rate | C127: 9 | D127: =VLOOKUP(C127,EconomicVariables!A:B,2,FALSE) -> Economic Growth (LRAS, PPC) | E127: increase | F127: =F119 -> Investment与利率反向，长期会影响capital stock资本存量（属于资源数量）和潜在产能。（Expansionary monetary policy刺激经济，降利率，增加AD）
A128: 16 | B128: =VLOOKUP(A128,PolicyActions!A:B,2,FALSE) -> Decrease interest on reserves | C128: 1 | D128: =VLOOKUP(C128,EconomicVariables!A:B,2,FALSE) -> Aggregate Demand | E128: increase | F128: =F120 -> Expansionary monetary policy刺激经济，通过降利率，增加interest-sensitive private spending和AD
A129: 16 | B129: =VLOOKUP(A129,PolicyActions!A:B,2,FALSE) -> Decrease interest on reserves | C129: 2 | D129: =VLOOKUP(C129,EconomicVariables!A:B,2,FALSE) -> Price Level | E129: increase | F129: =F121 -> Expansionary monetary policy刺激经济，降利率，增加AD，见AD-AS diagram
A130: 16 | B130: =VLOOKUP(A130,PolicyActions!A:B,2,FALSE) -> Decrease interest on reserves | C130: 3 | D130: =VLOOKUP(C130,EconomicVariables!A:B,2,FALSE) -> Real GDP | E130: increase | F130: =F122 -> Expansionary monetary policy刺激经济，降利率，增加AD，见AD-AS diagram
A131: 16 | B131: =VLOOKUP(A131,PolicyActions!A:B,2,FALSE) -> Decrease interest on reserves | C131: 4 | D131: =VLOOKUP(C131,EconomicVariables!A:B,2,FALSE) -> Unemployment Rate | E131: decrease | F131: =F123 -> 失业率通常与real GDP反向。（Expansionary monetary policy刺激经济，降利率，增加AD，见AD-AS diagram）
A132: 16 | B132: =VLOOKUP(A132,PolicyActions!A:B,2,FALSE) -> Decrease interest on reserves | C132: 6 | D132: =VLOOKUP(C132,EconomicVariables!A:B,2,FALSE) -> Interest Rate | E132: decrease | F132: =F124 -> Expansionary monetary policy降利率。Discount rate（federal funds rate上限）和IOR（federal funds rate下限）属于administered interest rate，央行可直接设定，用于调控市场利率的基准federal funds rate（见reserve market diagram)。 这三者都属于policy rate。
A133: 16 | B133: =VLOOKUP(A133,PolicyActions!A:B,2,FALSE) -> Decrease interest on reserves | C133: 7 | D133: =VLOOKUP(C133,EconomicVariables!A:B,2,FALSE) -> Bond Price | E133: increase | F133: =F125 -> 债券价格与利率反向。（Expansionary monetary policy刺激经济，降利率，增加AD）
A134: 16 | B134: =VLOOKUP(A134,PolicyActions!A:B,2,FALSE) -> Decrease interest on reserves | C134: 8 | D134: =VLOOKUP(C134,EconomicVariables!A:B,2,FALSE) -> Interest-sensitive Private Spending (Investment & Consumption) | E134: increase | F134: =F126 -> Interest-sensitive Private Spending (Investment & Consumption)与利率反向。（Expansionary monetary policy刺激经济，降利率，增加AD）
A135: 16 | B135: =VLOOKUP(A135,PolicyActions!A:B,2,FALSE) -> Decrease interest on reserves | C135: 9 | D135: =VLOOKUP(C135,EconomicVariables!A:B,2,FALSE) -> Economic Growth (LRAS, PPC) | E135: increase | F135: =F127 -> Investment与利率反向，长期会影响capital stock资本存量（属于资源数量）和潜在产能。（Expansionary monetary policy刺激经济，降利率，增加AD）
A136: 17 | B136: =VLOOKUP(A136,PolicyActions!A:B,2,FALSE) -> Decrease administered interest rates | C136: 1 | D136: =VLOOKUP(C136,EconomicVariables!A:B,2,FALSE) -> Aggregate Demand | E136: increase | F136: =F128 -> Expansionary monetary policy刺激经济，通过降利率，增加interest-sensitive private spending和AD
... A143: 17 | B143: =VLOOKUP(A143,PolicyActions!A:B,2,FALSE) -> Decrease administered interest rates | C143: 9 | D143: =VLOOKUP(C143,EconomicVariables!A:B,2,FALSE) -> Economic Growth (LRAS, PPC) | E143: increase | F143: =F135 -> Investment与利率反向，长期会影响capital stock资本存量（属于资源数量）和潜在产能。（Expansionary monetary policy刺激经济，降利率，增加AD）
A144: 18 | B144: =VLOOKUP(A144,PolicyActions!A:B,2,FALSE) -> Contractionary monetary policy | C144: 1 | D144: =VLOOKUP(C144,EconomicVariables!A:B,2,FALSE) -> Aggregate Demand | E144: decrease | F144: Contractionary monetary policy抑制经济，通过升利率，减少interest-sensitive private spending和AD
A145: 18 | B145: =VLOOKUP(A145,PolicyActions!A:B,2,FALSE) -> Contractionary monetary policy | C145: 2 | D145: =VLOOKUP(C145,EconomicVariables!A:B,2,FALSE) -> Price Level | E145: decrease | F145: Contractionary monetary policy抑制经济，升利率，减少AD，见AD-AS diagram
A146: 18 | B146: =VLOOKUP(A146,PolicyActions!A:B,2,FALSE) -> Contractionary monetary policy | C146: 3 | D146: =VLOOKUP(C146,EconomicVariables!A:B,2,FALSE) -> Real GDP | E146: decrease | F146: Contractionary monetary policy抑制经济，升利率，减少AD，见AD-AS diagram
A147: 18 | B147: =VLOOKUP(A147,PolicyActions!A:B,2,FALSE) -> Contractionary monetary policy | C147: 4 | D147: =VLOOKUP(C147,EconomicVariables!A:B,2,FALSE) -> Unemployment Rate | E147: increase | F147: 失业率通常与real GDP反向。（Contractionary monetary policy抑制经济，升利率，减少AD，见AD-AS diagram）
A148: 18 | B148: =VLOOKUP(A148,PolicyActions!A:B,2,FALSE) -> Contractionary monetary policy | C148: 5 | D148: =VLOOKUP(C148,EconomicVariables!A:B,2,FALSE) -> Money Supply | E148: decrease | F148: Contractionary monetary policy中sell bonds可减少monetary base，提高reserve requirement可降低money multiplier和money supply
A149: 18 | B149: =VLOOKUP(A149,PolicyActions!A:B,2,FALSE) -> Contractionary monetary policy | C149: 6 | D149: =VLOOKUP(C149,EconomicVariables!A:B,2,FALSE) -> Interest Rate | E149: increase | F149: Contractionary monetary policy减少money supply，提高利率（见money market diagram & reserve market diagram)
A150: 18 | B150: =VLOOKUP(A150,PolicyActions!A:B,2,FALSE) -> Contractionary monetary policy | C150: 7 | D150: =VLOOKUP(C150,EconomicVariables!A:B,2,FALSE) -> Bond Price | E150: decrease | F150: 债券价格与利率反向。（Contractionary monetary policy抑制经济，升利率，减少AD）
A151: 18 | B151: =VLOOKUP(A151,PolicyActions!A:B,2,FALSE) -> Contractionary monetary policy | C151: 8 | D151: =VLOOKUP(C151,EconomicVariables!A:B,2,FALSE) -> Interest-sensitive Private Spending (Investment & Consumption) | E151: decrease | F151: Interest-sensitive Private Spending (Investment & Consumption)与利率反向。（Contractionary monetary policy抑制经济，升利率，减少AD）
A152: 18 | B152: =VLOOKUP(A152,PolicyActions!A:B,2,FALSE) -> Contractionary monetary policy | C152: 9 | D152: =VLOOKUP(C152,EconomicVariables!A:B,2,FALSE) -> Economic Growth (LRAS, PPC) | E152: decrease | F152: Investment与利率反向，长期会影响capital stock资本存量（属于资源数量）和潜在产能。（Contractionary monetary policy抑制经济，升利率，减少AD）
A153: 19 | B153: =VLOOKUP(A153,PolicyActions!A:B,2,FALSE) -> Increase required reserve ratio | C153: 1 | D153: =VLOOKUP(C153,EconomicVariables!A:B,2,FALSE) -> Aggregate Demand | E153: decrease | F153: =F144 -> Contractionary monetary policy抑制经济，通过升利率，减少interest-sensitive private spending和AD
A154: 19 | B154: =VLOOKUP(A154,PolicyActions!A:B,2,FALSE) -> Increase required reserve ratio | C154: 2 | D154: =VLOOKUP(C154,EconomicVariables!A:B,2,FALSE) -> Price Level | E154: decrease | F154: =F145 -> Contractionary monetary policy抑制经济，升利率，减少AD，见AD-AS diagram
A155: 19 | B155: =VLOOKUP(A155,PolicyActions!A:B,2,FALSE) -> Increase required reserve ratio | C155: 3 | D155: =VLOOKUP(C155,EconomicVariables!A:B,2,FALSE) -> Real GDP | E155: decrease | F155: =F146 -> Contractionary monetary policy抑制经济，升利率，减少AD，见AD-AS diagram
A156: 19 | B156: =VLOOKUP(A156,PolicyActions!A:B,2,FALSE) -> Increase required reserve ratio | C156: 4 | D156: =VLOOKUP(C156,EconomicVariables!A:B,2,FALSE) -> Unemployment Rate | E156: increase | F156: =F147 -> 失业率通常与real GDP反向。（Contractionary monetary policy抑制经济，升利率，减少AD，见AD-AS diagram）
A157: 19 | B157: =VLOOKUP(A157,PolicyActions!A:B,2,FALSE) -> Increase required reserve ratio | C157: 5 | D157: =VLOOKUP(C157,EconomicVariables!A:B,2,FALSE) -> Money Supply | E157: decrease | F157: =F148 -> Contractionary monetary policy中sell bonds可减少monetary base，提高reserve requirement可降低money multiplier和money supply
A158: 19 | B158: =VLOOKUP(A158,PolicyActions!A:B,2,FALSE) -> Increase required reserve ratio | C158: 6 | D158: =VLOOKUP(C158,EconomicVariables!A:B,2,FALSE) -> Interest Rate | E158: increase | F158: =F149 -> Contractionary monetary policy减少money supply，提高利率（见money market diagram & reserve market diagram)
A159: 19 | B159: =VLOOKUP(A159,PolicyActions!A:B,2,FALSE) -> Increase required reserve ratio | C159: 7 | D159: =VLOOKUP(C159,EconomicVariables!A:B,2,FALSE) -> Bond Price | E159: decrease | F159: =F150 -> 债券价格与利率反向。（Contractionary monetary policy抑制经济，升利率，减少AD）
A160: 19 | B160: =VLOOKUP(A160,PolicyActions!A:B,2,FALSE) -> Increase required reserve ratio | C160: 8 | D160: =VLOOKUP(C160,EconomicVariables!A:B,2,FALSE) -> Interest-sensitive Private Spending (Investment & Consumption) | E160: decrease | F160: =F151 -> Interest-sensitive Private Spending (Investment & Consumption)与利率反向。（Contractionary monetary policy抑制经济，升利率，减少AD）
A161: 19 | B161: =VLOOKUP(A161,PolicyActions!A:B,2,FALSE) -> Increase required reserve ratio | C161: 9 | D161: =VLOOKUP(C161,EconomicVariables!A:B,2,FALSE) -> Economic Growth (LRAS, PPC) | E161: decrease | F161: =F152 -> Investment与利率反向，长期会影响capital stock资本存量（属于资源数量）和潜在产能。（Contractionary monetary policy抑制经济，升利率，减少AD）
A162: 20 | B162: =VLOOKUP(A162,PolicyActions!A:B,2,FALSE) -> Increase reserve requirement | C162: 1 | D162: =VLOOKUP(C162,EconomicVariables!A:B,2,FALSE) -> Aggregate Demand | E162: decrease | F162: =F153 -> Contractionary monetary policy抑制经济，通过升利率，减少interest-sensitive private spending和AD
A163: 20 | B163: =VLOOKUP(A163,PolicyActions!A:B,2,FALSE) -> Increase reserve requirement | C163: 2 | D163: =VLOOKUP(C163,EconomicVariables!A:B,2,FALSE) -> Price Level | E163: decrease | F163: =F154 -> Contractionary monetary policy抑制经济，升利率，减少AD，见AD-AS diagram
A164: 20 | B164: =VLOOKUP(A164,PolicyActions!A:B,2,FALSE) -> Increase reserve requirement | C164: 3 | D164: =VLOOKUP(C164,EconomicVariables!A:B,2,FALSE) -> Real GDP | E164: decrease | F164: =F155 -> Contractionary monetary policy抑制经济，升利率，减少AD，见AD-AS diagram
...

Sheet DiagramData
A1: id | B1: name | C1: curves
A2: 1 | B2: AD-AS Diagram | C2: Aggregate Demand,Short-run Aggregate Supply,Long-run Aggregate Supply
A3: 2 | B3: Money Market Diagram | C3: Money Supply,Money Demand
A4: 3 | B4: Loanable Funds Market | C4: Supply of Loanable Funds,Demand for Loanable Funds
A5: 4 | B5: Foreign Exchange Market | C5: Supply of Dollars,Demand for Dollars
A6: 5 | B6: Phillips Curve | C6: Short-run Phillips Curve,Long-run Phillips Curve

Sheet EconomicEvents
A1: id | B1: event | C1: affectedDiagram | D1: affectedCurve | E1: effect | F1: explanation | H1: 35 | I1: Expansionary fiscal policy (或increase government spending) | J1: Money Market Diagram | K1: Money Demand | L1: increase
A2: 1 | B2: Consumer confidence decreases | C2: AD-AS Diagram | D2: Aggregate Demand | E2: decrease
A3: 2 | B3: An increase in exports | C3: AD-AS Diagram | D3: Aggregate Demand | E3: increase
A4: 3 | B4: Increased spending by businesses on computers | C4: AD-AS Diagram | D4: Aggregate Demand | E4: increase
A5: 4 | B5: A decrease in household income | C5: AD-AS Diagram | D5: Aggregate Demand | E5: decrease
A6: 5 | B6: Consumers have large unpaid balances on their credit cards. | C6: AD-AS Diagram | D6: Aggregate Demand | E6: decrease
A7: 6 | B7: Consumers’ wealth is increased by changes in the stock market | C7: AD-AS Diagram | D7: Aggregate Demand | E7: increase
A8: 7 | B8: Population | C8: AD-AS Diagram | D8: Aggregate Demand | E8: increase
A9: 8 | B9: An increase in military spending | C9: AD-AS Diagram | D9: Aggregate Demand | E9: increase
A10: 9 | B10: A major trading partner experiences a recession | C10: AD-AS Diagram | D10: Aggregate Demand | E10: decrease
A11: 10 | B11: The optimism of business firms | C11: AD-AS Diagram | D11: Aggregate Demand | E11: increase
A12: 11 | B12: A increase in the expected rate of inflation | C12: AD-AS Diagram | D12: Aggregate Demand | E12: increase
A13: 12 | B13: Depreciation of this country's currency on the foreign exchange market | C13: AD-AS Diagram | D13: Aggregate Demand | E13: increase
... A51: 50 | B51: The economy is facing political instability. | C51: Loanable Funds Market | D51: Supply of Loanable Funds | E51: decrease
